dutch_med_hips/__init__.py
dutch_med_hips/cli.py
dutch_med_hips/core.py
dutch_med_hips/locale.py
dutch_med_hips/schema.py
dutch_med_hips/settings.py
dutch_med_hips/surrogates.py
dutch_med_hips-1.0.1.dist-info/licenses/LICENSE
dutch_med_hips-1.0.1.dist-info/METADATA
dutch_med_hips-1.0.1.dist-info/WHEEL
dutch_med_hips-1.0.1.dist-info/entry_points.txt
dutch_med_hips-1.0.1.dist-info/top_level.txt
dutch_med_hips-1.0.1.dist-info/RECORD
