Metadata-Version: 2.4
Name: dutch-med-hips
Version: 1.0.1
Summary: A hiding in plain sight module for Dutch medical text.
Author-email: Luc Builtjes <luc.builtjes@radboudumc.nl>
License:                     GNU GENERAL PUBLIC LICENSE
Requires-Python: >=3.7
License-File: LICENSE
Requires-Dist: numpy
Requires-Dist: pandas
Requires-Dist: scikit-learn
Requires-Dist: unidecode
Requires-Dist: jsonlines
Requires-Dist: faker
Requires-Dist: typo
Provides-Extra: dev
Requires-Dist: pytest; extra == "dev"
Requires-Dist: pytest-cov; extra == "dev"
Requires-Dist: twine; extra == "dev"
Requires-Dist: build; extra == "dev"
Dynamic: license-file
